gzm_client/__init__.py
gzm_client/cli.py
gzm_client/client.py
gzm_client/constants.py
gzm_client/transportation/__init__.py
gzm_client/transportation/junction.py
gzm_client/transportation/parsers.py
gzm_client/transportation/stop.py
gzm_client/transportation/vehicle.py
gzm_client/transportation/bikes/__init__.py
gzm_client/transportation/bikes/bike.py
gzm_client/transportation/bikes/station.py
gzm_client/utils/__init__.py
gzm_client/utils/sql_cache.py
gzm_client-0.2.3.dist-info/licenses/LICENSE
gzm_client-0.2.3.dist-info/METADATA
gzm_client-0.2.3.dist-info/WHEEL
gzm_client-0.2.3.dist-info/entry_points.txt
gzm_client-0.2.3.dist-info/top_level.txt
gzm_client-0.2.3.dist-info/RECORD
