Metadata-Version: 2.4
Name: gzm-client
Version: 0.2.3
Summary: GZM Transport Client with CLI or Python API
Author-email: Kuba Kochaniak <kkuba91@o2.pl>
Requires-Python: >=3.10
License-File: LICENSE
Dynamic: license-file
